[
    {"regex": "\\\\N", "replace": " "},
    {"regex": "\\\\n", "replace": " "},
    {"regex": "{\\\\i1}", "replace": ""},
    {"regex": "\\\\i1", "replace": ""},
    {"regex": "{\\\\i0}", "replace": ""},
    {"regex": "{an8}", "replace": "{\\\\an8} "},
    {"regex": "<font.olor=\"#ffff00\">", "replace": "{\\\\an8} "},
    {"regex": "<font color=\"#ffff00\">", "replace": "{\\\\an8} "},
    {"regex": "{\\\\an}", "replace": ""},
    {"regex": " +", "replace": " "},
    {"regex": "!'!", "replace": "!"},
    {"regex": "'!", "replace": "!"},
    {"regex": "!'", "replace": "!"},
    {"regex": "! \\.", "replace": "!.."},
    {"regex": "\\. ,", "replace": "."},
    {"regex": " \\.", "replace": "."},
    {"regex": "чЧ", "replace": "Ч"},
    {"regex": "ОЙ", "replace": "Ой"},
    {"regex": "<«", "replace": "«"},
    {"regex": "« ", "replace": "«"},
    {"regex": "«<", "replace": "«"},
    {"regex": "<<", "replace": "«"},
    {"regex": "<‹", "replace": "«"},
    {"regex": " »", "replace": "»"},
    {"regex": "»>›", "replace": "»"},
    {"regex": "»>", "replace": "»"},
    {"regex": "››", "replace": "»"},
    {"regex": "\\МАКАМТМ", "replace": "Wakanim"},
    {"regex": "\\\\\\\\Wakanim", "replace": "Wakanim"},
    {"regex": "'\\n", "replace": "!\\n"},
    {"regex": " \\?", "replace": "?"},
    {"regex": " !", "replace": "!"},
    {"regex": "©бпасибо", "replace": "Спасибо"},
    {"regex": "[.,‚„][.,‚„]", "replace": "..."},
    {"regex": "[.,‚„][.,‚„][.,‚„]", "replace": "..."},
    {"regex": "[.,‚„][.,‚„][.,‚„][.,‚„]", "replace": "..."},
    {"regex": "@н", "replace": "Он"}
]